sopic/__init__.py
sopic/gui/__init__.py
sopic/gui/logger_widget.py
sopic/gui/main_window.py
sopic/gui/settings_dialog_widget.py
sopic/gui/settings_widgets.py
sopic/gui/start_screen_widget.py
sopic/gui/station_info_widget.py
sopic/gui/station_status_widget.py
sopic/gui/steps_viewer_widget.py
sopic/station.py
sopic/step.py
sopic/utils/__init__.py
sopic/utils/dag.py
sopic/utils/logger.py
sopic/utils/settings.py
sopic-1.0.0.dist-info/LICENSE
sopic-1.0.0.dist-info/METADATA
sopic-1.0.0.dist-info/WHEEL
sopic-1.0.0.dist-info/RECORD
